nn_mouse/__init__.py
nn_mouse/path.onnx
nn_mouse/predict.py
nn_mouse/py.typed
nn_mouse/time.onnx
nn_mouse-1.0.2.dist-info/licenses/LICENSE
nn_mouse-1.0.2.dist-info/METADATA
nn_mouse-1.0.2.dist-info/WHEEL
nn_mouse-1.0.2.dist-info/top_level.txt
nn_mouse-1.0.2.dist-info/RECORD
