Metadata-Version: 2.4
Name: nn-mouse
Version: 1.0.2
Summary: Neural network based humanized mouse movements
Author-email: Pradish Bijukchhe <pradish@sandbox.com.np>
License: Copyright (c) 2018 The Python Packaging Authority
Project-URL: Homepage, https://github.com/sandbox-pokhara/nn-mouse
Project-URL: Issues, https://github.com/sandbox-pokhara/nn-mouse/issues
Classifier: Programming Language :: Python :: 3
Requires-Python: >=3
License-File: LICENSE
Provides-Extra: opencv
Requires-Dist: opencv-python; extra == "opencv"
Provides-Extra: opencv-contrib
Requires-Dist: opencv-contrib-python; extra == "opencv-contrib"
Dynamic: license-file
